natural_computing/__init__.py
natural_computing/data_preparation/__init__.py
natural_computing/data_preparation/dataset.py
natural_computing/data_preparation/scaler.py
natural_computing/network_utils/__init__.py
natural_computing/network_utils/codification.py
natural_computing/network_utils/factories.py
natural_computing/network_utils/objective_functions.py
natural_computing/neural_network/__init__.py
natural_computing/neural_network/activation_functions.py
natural_computing/neural_network/layers.py
natural_computing/neural_network/loss_functions.py
natural_computing/neural_network/network.py
natural_computing/neural_network/regularization.py
natural_computing/neural_network/utils.py
natural_computing/objective_functions/__init__.py
natural_computing/objective_functions/base_function.py
natural_computing/objective_functions/benchmarks.py
natural_computing/objective_functions/polynomial.py
natural_computing/optimization/__init__.py
natural_computing/optimization/base_optimizer.py
natural_computing/optimization/differential_evolution.py
natural_computing/optimization/evolution_strategy.py
natural_computing/optimization/genetic_algorithm.py
natural_computing/optimization/particle_swarm.py
natural_computing/plotting/__init__.py
natural_computing/plotting/fit_value.py
natural_computing/plotting/plotter.py
natural_computing/plotting/polynomial.py
natural_computing/utils/__init__.py
natural_computing/utils/binary.py
natural_computing/utils/data_generation.py
natural_computing/utils/math.py
natural_computing-0.6.0.dist-info/METADATA
natural_computing-0.6.0.dist-info/WHEEL
natural_computing-0.6.0.dist-info/RECORD
