Metadata-Version: 2.1
Name: natural-computing
Version: 0.6.0
Summary: 
Author: Gabriel Soares Baptista
Author-email: gsoaresbaptista@gmail.com
Requires-Python: >=3.9,<4.0
Classifier: Programming Language :: Python :: 3
Classifier: Programming Language :: Python :: 3.9
Classifier: Programming Language :: Python :: 3.10
Classifier: Programming Language :: Python :: 3.11
Requires-Dist: matplotlib (>=3.7.2,<4.0.0)
Requires-Dist: pandas (>=2.1.0,<3.0.0)
Requires-Dist: requests (>=2.31.0,<3.0.0)
